{".class": "MypyFile", "_fullname": "app.models", "_name": null, "is_stub": false, "names": {".class": "SymbolTable", "Comment": {".class": "SymbolTableNode", "kind": "Gdef", "node": {".class": "TypeInfo", "_promote": null, "abstract_attributes": [], "bases": ["builtins.object"], "declared_metaclass": null, "defn": {".class": "ClassDef", "fullname": "app.models.Comment", "metaclass": null, "name": "Comment", "type_vars": []}, "flags": ["fallback_to_any"], "fullname": "app.models.Comment", "metaclass_type": null, "module_name": "app.models", "names": {".class": "SymbolTable", "comment": {".class": "SymbolTableNode", "kind": "Mdef", "node": {".class": "Var", "flags": ["is_ready", "is_initialized_in_class"], "fullname": "app.models.Comment.comment", "name": "comment", "type": {".class": "AnyType"}}}, "document": {".class": "SymbolTableNode", "kind": "Mdef", "node": {".class": "Var", "flags": ["is_ready", "is_initialized_in_class"], "fullname": "app.models.Comment.document", "name": "document", "type": {".class": "AnyType"}}}, "time": {".class": "SymbolTableNode", "kind": "Mdef", "node": {".class": "Var", "flags": ["is_ready", "is_initialized_in_class"], "fullname": "app.models.Comment.time", "name": "time", "type": {".class": "AnyType"}}}}, "tuple_type": null, "type_vars": [], "typeddict_type": null}}, "GetImage": {".class": "SymbolTableNode", "kind": "Gdef", "node": {".class": "TypeInfo", "_promote": null, "abstract_attributes": [], "bases": ["builtins.object"], "declared_metaclass": null, "defn": {".class": "ClassDef", "fullname": "app.models.GetImage", "metaclass": null, "name": "GetImage", "type_vars": []}, "flags": ["fallback_to_any"], "fullname": "app.models.GetImage", "metaclass_type": null, "module_name": "app.models", "names": {".class": "SymbolTable", "caption": {".class": "SymbolTableNode", "kind": "Mdef", "node": {".class": "Var", "flags": ["is_ready", "is_initialized_in_class"], "fullname": "app.models.GetImage.caption", "name": "caption", "type": {".class": "AnyType"}}}, "image": {".class": "SymbolTableNode", "kind": "Mdef", "node": {".class": "Var", "flags": ["is_ready", "is_initialized_in_class"], "fullname": "app.models.GetImage.image", "name": "image", "type": {".class": "AnyType"}}}, "image_url": {".class": "SymbolTableNode", "kind": "Mdef", "node": {".class": "FuncDef", "arg_kinds": [0], "arg_names": ["self"], "flags": [], "fullname": "app.models.GetImage.image_url", "name": "image_url", "type": null}}, "uploaded_at": {".class": "SymbolTableNode", "kind": "Mdef", "node": {".class": "Var", "flags": ["is_ready", "is_initialized_in_class"], "fullname": "app.models.GetImage.uploaded_at", "name": "uploaded_at", "type": {".class": "AnyType"}}}, "uploaded_by": {".class": "SymbolTableNode", "kind": "Mdef", "node": {".class": "Var", "flags": ["is_ready", "is_initialized_in_class"], "fullname": "app.models.GetImage.uploaded_by", "name": "uploaded_by", "type": {".class": "AnyType"}}}}, "tuple_type": null, "type_vars": [], "typeddict_type": null}}, "__doc__": {".class": "SymbolTableNode", "kind": "Gdef", "node": {".class": "Var", "flags": ["is_ready"], "fullname": "app.models.__doc__", "name": "__doc__", "type": "builtins.str"}}, "__file__": {".class": "SymbolTableNode", "kind": "Gdef", "node": {".class": "Var", "flags": ["is_ready"], "fullname": "app.models.__file__", "name": "__file__", "type": "builtins.str"}}, "__name__": {".class": "SymbolTableNode", "kind": "Gdef", "node": {".class": "Var", "flags": ["is_ready"], "fullname": "app.models.__name__", "name": "__name__", "type": "builtins.str"}}, "__package__": {".class": "SymbolTableNode", "kind": "Gdef", "node": {".class": "Var", "flags": ["is_ready"], "fullname": "app.models.__package__", "name": "__package__", "type": "builtins.str"}}, "models": {".class": "SymbolTableNode", "kind": "Gdef", "node": {".class": "Var", "flags": ["is_ready", "is_suppressed_import"], "fullname": "app.models.models", "name": "models", "type": {".class": "AnyType"}}}}, "path": "/home/basecamp/Django/December/finstagram/app/models.py"}
