{"id": "app.views", "path": "/home/treyshel/Projects/django/Fake-Instagram/app/views.py", "mtime": 1514993474, "size": 2502, "hash": "d786953e0a66d2cb96131219264d03f2", "data_mtime": 1514994682, "dependencies": ["app.forms", "app.models", "builtins"], "suppressed": ["django.shortcuts", "django.views", "PIL", "resizeimage"], "child_modules": [], "options": {"disallow_any_decorated": false, "disallow_any_unimported": false, "show_none_errors": true, "ignore_missing_imports": true, "disallow_any_explicit": false, "quick_and_dirty": false, "ignore_errors": false, "platform": "linux", "no_implicit_optional": false, "disallow_subclassing_any": false, "warn_return_any": false, "disallow_untyped_calls": false, "disallow_any_generics": false, "warn_no_return": true, "follow_imports": "silent", "strict_optional": false, "disallow_untyped_defs": false, "check_untyped_defs": false, "disallow_any_expr": false, "strict_optional_whitelist": null, "disallow_untyped_decorators": false, "strict_boolean": false}, "dep_prios": [5, 5, 5], "interface_hash": "3deba3bc1c6268108cbe92447e0792f3", "version_id": "0.560", "ignore_all": true}
